alex_asr
