Metadata-Version: 1.1
Name: alex-asr
Version: 1.0.4
Summary: Incremental speech recognition decoder for Kaldi NNET2 and GMM models.
Home-page: https://github.com/UFAL-DSG/alex-asr
Author: Charles University in Prague (Lukas Zilka)
Author-email: lukas@zilka.me
License: Apache Software License 2.0
Download-URL: https://github.com/UFAL-DSG/alex-asr/archive/v1.0.4.tar.gz
Keywords: asr,speech recognition,decoder,speech
Platform: UNKNOWN
Classifier: Programming Language :: Python :: 2
Classifier:         Programming Language :: Python :: 3
Classifier:         License :: OSI Approved :: Apache Software License
Classifier:         Operating System :: POSIX :: Linux
Classifier:         Topic :: Multimedia :: Sound/Audio :: Speech
Classifier:         Topic :: Scientific/Engineering
Classifier:         Intended Audience :: Developers
Classifier:         Intended Audience :: Science/Research
Classifier:         Intended Audience :: Telecommunications Industry
Classifier:         Environment :: Console
